kamutils/__init__.py
kamutils/analyse.py
kamutils/exceptions.py
kamutils/misc.py
kamutils/spatial.py
kamutils-1.1.0.dist-info/METADATA
kamutils-1.1.0.dist-info/WHEEL
kamutils-1.1.0.dist-info/licenses/LICENSE
kamutils-1.1.0.dist-info/RECORD
