Metadata-Version: 2.1
Name: kamutils
Version: 1.1.0
Summary: Converts Oracle SDO_GEOMETRY into spatial objects which implements the __geo_interface__ protocol (GeoJSON like dict). Supports also WKT conversion.
Author-email: Kam One <info.kamutils@gmail.com>
License-Expression: CECILL-B
License-File: LICENSE
Classifier: Development Status :: 5 - Production/Stable
Classifier: Intended Audience :: Developers
Classifier: License :: CeCILL-B Free Software License Agreement (CECILL-B)
Classifier: Operating System :: OS Independent
Classifier: Programming Language :: Python :: 3.7
Classifier: Topic :: Database
Classifier: Topic :: Scientific/Engineering :: GIS
Requires-Python: >=3.7
